pass_calculator/__init__.py
pass_calculator/calculator.py
pass_calculator/orbitalpass.py
pass_calculator-1.0.1.dist-info/METADATA
pass_calculator-1.0.1.dist-info/WHEEL
pass_calculator-1.0.1.dist-info/top_level.txt
pass_calculator-1.0.1.dist-info/RECORD
